triangle_cubature/__init__.py
triangle_cubature/cubature_rule.py
triangle_cubature/integrate.py
triangle_cubature/rule_factory.py
triangle_cubature/transformations.py
triangle_cubature-1.2.0.dist-info/LICENSE
triangle_cubature-1.2.0.dist-info/METADATA
triangle_cubature-1.2.0.dist-info/WHEEL
triangle_cubature-1.2.0.dist-info/top_level.txt
triangle_cubature-1.2.0.dist-info/RECORD
