Metadata-Version: 2.1
Name: triangle_cubature
Version: 1.2.0
Summary: cubature rules on triangles
Author-email: Raphael Leu <raphaelleu95@gmail.com>
Project-URL: Homepage, https://github.com/leuraph/triangle_cubature
Project-URL: Issues, https://github.com/leuraph/triangle_cubature/issues
Classifier: Programming Language :: Python :: 3
Classifier: License :: OSI Approved :: MIT License
Classifier: Operating System :: OS Independent
Requires-Python: >=3.9.18
License-File: LICENSE
Requires-Dist: numpy
Requires-Dist: p1afempy
